{
    "bitcoin": {
        "name": "Bitcoin",
        "canonicalName": "Bitcoin",
        "symbol": "BTC",
        "family": "bitcoin",
        "website": "https://www.bitcoin.org/",
        "market": "https://coinmarketcap.com/currencies/bitcoin/",
        "twitter": "https://twitter.com/bitcoin",
        "telegram": "",
        "discord": "",
        "coinbaseHasher": {
            "hash": "sha256d"
        },
        "headerHasher": {
            "hash": "sha256d"
        },
        "blockHasher": {
            "hash": "reverse",
            "args": [
                {
                    "hash": "sha256d"
                }
            ]
        },
        "coinbaseIgnoreAuxFlags": true,
        "explorerBlockLink": "https://www.blockchain.com/btc/block/$hash$",
        "explorerTxLink": "https://www.blockchain.com/btc/tx/{0}",
        "explorerAccountLink": "https://www.blockchain.com/btc/address/{0}"
    },
    "bitcoin-cash": {
        "name": "Bitcoin Cash",
        "canonicalName": "Bitcoin-Cash",
        "symbol": "BCH",
        "family": "bitcoin",
        "website": "",
        "market": "",
        "twitter": "",
        "telegram": "",
        "discord": "",
        "coinbaseHasher": {
            "hash": "sha256d"
        },
        "headerHasher": {
            "hash": "sha256d"
        },
        "blockHasher": {
            "hash": "reverse",
            "args": [
                {
                    "hash": "sha256d"
                }
            ]
        },
        "explorerBlockLink": "https://bchblockexplorer.com/block/$height$",
        "explorerTxLink": "https://bchblockexplorer.com/tx/{0}",
        "explorerAccountLink": "https://bchblockexplorer.com/address/{0}"
    },
    "digibyte-sha256": {
        "name": "Digibyte Sha256",
        "canonicalName": "Digibyte",
        "symbol": "DGB",
        "family": "bitcoin",
        "website": "https://digibyte.org/",
        "market": "https://coinmarketcap.com/currencies/digibyte/",
        "twitter": "https://twitter.com/digibytecoin",
        "telegram": "https://t.me/DigiByteCoin",
        "discord": "",
        "coinbaseHasher": {
            "hash": "sha256d"
        },
        "headerHasher": {
            "hash": "sha256d"
        },
        "blockHasher": {
            "hash": "reverse",
            "args": [
                {
                    "hash": "sha256d"
                }
            ]
        },
        "blockTemplateRpcExtraParams": [
            "sha256d"
        ],
        "explorerBlockLink": "https://chainz.cryptoid.info/dgb/block.dws?$height$.htm",
        "explorerTxLink": "https://chainz.cryptoid.info/dgb/tx.dws?{0}.htm",
        "explorerAccountLink": "https://chainz.cryptoid.info/dgb/address.dws?{0}.htm"
    },
    "dash": {
        "name": "Dash",
        "canonicalName": "Dash",
        "symbol": "DASH",
        "family": "bitcoin",
        "website": "",
        "market": "",
        "twitter": "",
        "telegram": "",
        "discord": "",
        "coinbaseHasher": {
            "hash": "sha256d"
        },
        "headerHasher": {
            "hash": "x11"
        },
        "blockHasher": {
            "hash": "reverse",
            "args": [
                {
                    "hash": "x11"
                }
            ]
        },
        "hasMasterNodes": true,
        "explorerBlockLink": "https://chainz.cryptoid.info/dash/block.dws?$height$.htm",
        "explorerTxLink": "https://chainz.cryptoid.info/dash/tx.dws?{0}.htm",
        "explorerAccountLink": "https://chainz.cryptoid.info/dash/address.dws?{0}.htm"
    }
}
